{"slug": "06-neon-grid", "bg": "#05060a", "bg2": "rgba(13,18,28,.6)", "ink": "#e8f6ff", "mut": "#9fb6c6", "accent": "#00f0ff", "accent2": "#ff2bd6", "accent3": "#7b5cff", "line": "rgba(0,240,255,.18)", "glass": "rgba(5,6,10,.6)", "body_font": "'Space Grotesk',sans-serif", "heading_font": "'Orbitron',sans-serif", "heading_ls": ".02em", "heading_lh": "1.04", "card_radius": "14px", "button_radius": "40px", "button_shape": "pill", "ribbon_bg": "#00f0ff", "ribbon_color": "#04060c", "ribbon_text": "American Barber Institute · Particle-network barbering education · Next: First Monday", "decoration": "particle-network", "vibe": "Neon grid with particle networks on deep navy", "h1_effect": "neon-shadow", "media_style": "grid-tilt"}
